MANIFEST.in
README.md
setup.py
django_simple_redis_admin.egg-info/PKG-INFO
django_simple_redis_admin.egg-info/SOURCES.txt
django_simple_redis_admin.egg-info/dependency_links.txt
django_simple_redis_admin.egg-info/not-zip-safe
django_simple_redis_admin.egg-info/top_level.txt
redis_admin/__init__.py
redis_admin/admin.py
redis_admin/compat.py
redis_admin/models.py
redis_admin/templates/redis_admin/delete_confirmation.html
redis_admin/templates/redis_admin/delete_selected_confirmation.html
redis_admin/templates/redis_admin/index.html
redis_admin/templates/redis_admin/key.html
redis_admin/templatetags/__init__.py
redis_admin/templatetags/compat.py
redis_admin/tests/__init__.py
redis_admin/tests/test_admin.py
redis_admin/tests/test_urls.py