Metadata-Version: 1.1
Name: django-simple-redis-admin
Version: 1.4.0
Summary: A django admin application to manage redis cache keys.
Home-page: https://github.com/nicholasserra/django-simple-redis-admin
Author: Nicholas Serra
Author-email: nick@528hazelwood.com
License: UNKNOWN
Platform: UNKNOWN
Classifier: Development Status :: 4 - Beta
Classifier: Environment :: Web Environment
Classifier: Intended Audience :: Developers
Classifier: License :: OSI Approved :: BSD License
Classifier: Operating System :: OS Independent
Classifier: Programming Language :: Python
Classifier: Framework :: Django
